InstallRelease/__init__.py
InstallRelease/cli.py
InstallRelease/cli_interact.py
InstallRelease/constants.py
InstallRelease/core.py
InstallRelease/data.py
InstallRelease/release_scorer.py
InstallRelease/state.py
InstallRelease/utils.py
install_release-0.6.0.dist-info/licenses/LICENSE
install_release-0.6.0.dist-info/METADATA
install_release-0.6.0.dist-info/WHEEL
install_release-0.6.0.dist-info/entry_points.txt
install_release-0.6.0.dist-info/top_level.txt
install_release-0.6.0.dist-info/RECORD
