Metadata-Version: 2.4
Name: install-release
Version: 0.6.0
Summary: Simple package manager to easily install, update and manage any command-line(CLI) tool directly from github releases
Author-email: Rishang <rishangbhavsarcs@gmail.com>
Project-URL: Homepage, https://github.com/Rishang/install-release
Project-URL: Documentation, https://github.com/Rishang/install-release
Project-URL: Repository, https://github.com/Rishang/install-release
Project-URL: Issues, https://github.com/Rishang/install-release/issues
Project-URL: Changelog, https://github.com/Rishang/install-release/release
Classifier: Intended Audience :: Information Technology
Classifier: Intended Audience :: System Administrators
Classifier: Operating System :: OS Independent
Classifier: Programming Language :: Python :: 3
Classifier: Programming Language :: Python
Classifier: Topic :: Software Development :: Libraries :: Python Modules
Classifier: Topic :: Software Development :: Libraries
Classifier: Topic :: Software Development :: Build Tools
Classifier: Topic :: Software Development
Classifier: Typing :: Typed
Classifier: Development Status :: 4 - Beta
Classifier: Intended Audience :: Developers
Requires-Python: >=3.9
License-File: LICENSE
Requires-Dist: python-magic>=0.4.27
Requires-Dist: requests>=2.32.5
Requires-Dist: rich>=14.1.0
Requires-Dist: typer>=0.17.3
Requires-Dist: zstandard>=0.24.0
Dynamic: license-file
